simple_note_taker/__init__.py
simple_note_taker/__main__.py
simple_note_taker/__version__.py
simple_note_taker/config.py
simple_note_taker/core/__init__.py
simple_note_taker/core/database.py
simple_note_taker/core/notes.py
simple_note_taker/core/reminders.py
simple_note_taker/help_texts.py
simple_note_taker/main.py
simple_note_taker/subcommands/__init__.py
simple_note_taker/subcommands/config.py
simple_note_taker-0.2.4.dist-info/entry_points.txt
simple_note_taker-0.2.4.dist-info/LICENSE
simple_note_taker-0.2.4.dist-info/WHEEL
simple_note_taker-0.2.4.dist-info/METADATA
simple_note_taker-0.2.4.dist-info/RECORD
