Metadata-Version: 2.1
Name: simple-note-taker
Version: 0.2.4
Summary: A simple CLI Notetaker with magic commands and options for centralization and summaries for teams
Home-page: https://github.com/GitToby/simple_note_taker
License: Apache-2.0
Author: Toby Devlin
Author-email: toby@tobydevlin.com
Requires-Python: >=3.6,<4.0
Classifier: Development Status :: 3 - Alpha
Classifier: License :: OSI Approved :: Apache Software License
Classifier: Programming Language :: Python :: 3
Classifier: Programming Language :: Python :: 3.6
Classifier: Programming Language :: Python :: 3.7
Classifier: Programming Language :: Python :: 3.8
Classifier: Programming Language :: Python :: 3.9
Requires-Dist: colorama (>=0.4.4,<0.5.0)
Requires-Dist: pydantic (>=1.8.1,<2.0.0)
Requires-Dist: pytest-cov (>=2.11.1,<3.0.0)
Requires-Dist: pytimeparse (>=1.1.8,<2.0.0)
Requires-Dist: rapidfuzz (>=1.2.1,<2.0.0)
Requires-Dist: tinydb (>=4.4.0,<5.0.0)
Requires-Dist: tinydb-serialization (>=2.1.0,<3.0.0)
Requires-Dist: typer (>=0.3.2,<0.4.0)
Project-URL: Repository, https://github.com/GitToby/simple_note_taker
